collibra_data_classification/__init__.py
collibra_data_classification/api_client.py
collibra_data_classification/configuration.py
collibra_data_classification/exceptions.py
collibra_data_classification/rest.py
collibra_data_classification/api/__init__.py
collibra_data_classification/api/data_classification_api.py
collibra_data_classification/models/__init__.py
collibra_data_classification/models/add_classification_match_request.py
collibra_data_classification/models/add_classification_matches_request.py
collibra_data_classification/models/add_classification_request.py
collibra_data_classification/models/change_classification_match_request.py
collibra_data_classification/models/change_classification_request.py
collibra_data_classification/models/classification.py
collibra_data_classification/models/classification_match.py
collibra_data_classification/models/classify_request.py
collibra_data_classification/models/find_classification_matches_request.py
collibra_data_classification/models/find_classifications_request.py
collibra_data_classification/models/job.py
collibra_data_classification/models/named_resource_reference_impl.py
collibra_data_classification/models/paged_response_classification.py
collibra_data_classification/models/paged_response_classification_match.py
collibra_data_classification-2.0.0.post5.dist-info/METADATA
collibra_data_classification-2.0.0.post5.dist-info/WHEEL
collibra_data_classification-2.0.0.post5.dist-info/top_level.txt
collibra_data_classification-2.0.0.post5.dist-info/RECORD
