Metadata-Version: 2.1
Name: collibra-data-classification
Version: 2.0.0.post5
Summary: Collibra Catalog classification API
Home-page: 
Author: OpenAPI Generator community
Author-email: team@openapitools.org
Keywords: OpenAPI,OpenAPI-Generator,Collibra Catalog classification API
Requires-Dist: urllib3 (>=1.15)
Requires-Dist: six (>=1.10)
Requires-Dist: certifi
Requires-Dist: python-dateutil
